CHANGELOG.txt
LICENCE.txt
MANIFEST.in
README.txt
setup.py
managecache/__init__.py
managecache.egg-info/PKG-INFO
managecache.egg-info/SOURCES.txt
managecache.egg-info/dependency_links.txt
managecache.egg-info/top_level.txt
managingcache.egg-info/SOURCES.txt
managingcache.egg-info/dependency_links.txt
managingcache.egg-info/top_level.txt